Helms.ipynb
MANIFEST.in
README.txt
SampleAnalysis.ipynb
VideoAnalysisWidget.ipynb
setup.cfg
setup.py
VideoAnalysis/Helms.py
VideoAnalysis/Helms.pyc
VideoAnalysis/Helms.py~
VideoAnalysis/__init__.py
VideoAnalysis/__init__.pyc
VideoAnalysis.egg-info/PKG-INFO
VideoAnalysis.egg-info/SOURCES.txt
VideoAnalysis.egg-info/dependency_links.txt
VideoAnalysis.egg-info/requires.txt
VideoAnalysis.egg-info/top_level.txt