Metadata-Version: 1.1
Name: VideoAnalysis
Version: 0.1.7
Summary: Widgets for analysis of worm videos
Home-page: https://pypi.python.org/pypi/VideoAnalysis
Author: Leon Avery
Author-email: lavery3@vcu.edu
License: UNKNOWN
Platform: UNKNOWN
Classifier: Development Status :: 2 - Pre-Alpha
Classifier: Environment :: Web Environment
Classifier: Framework :: IPython
Classifier: Intended Audience :: Developers
Classifier: Intended Audience :: Science/Research
Classifier: License :: Free for non-commercial use
Classifier: Programming Language :: Python
Classifier: Topic :: Software Development :: Widget Sets
Requires: ipython
Requires: PIL
Requires: hashlib
Requires: numpy
Requires: IPython
Requires: IPython.html
Requires: IPython.utils.traitlets
Requires: PIL
Requires: hashlib
Requires: numpy
Requires: scipy
Requires: h5py
Requires: skimage
Requires: matplotlib
Requires: ROIWidgets
Requires: Avery
